{
	"_description": "Diese Datei enth채lt alle Kartendaten f체r den Client",
	"Cards": {
		"MoneyCard": {
			"1": {
				"name": "Kupfer",
				"description": "Geld",
				"image": "1.png"
			},
			"2": {
				"name": "Silber",
				"description": "Geld",
				"image": "2.png"
			},
			"3": {
				"name": "Gold",
				"description": "Geld",
				"image": "3.png"
			}
		},
		"ValueCard": {
			"11": {
				"name": "Anwesen",
				"description": "Punkte",
				"image": "11.png"
			},
			"12": {
				"name": "Herzogtum",
				"description": "Punkte",
				"image": "12.png"
			},
			"13": {
				"name": "Provinz",
				"description": "Punkte",
				"image": "13.png"
			}
		},
		"ReactionCard": {
			"21": {
				"name": "Burggraben",
				"description": "+ 2 Karten, Wenn ein Mitspieler eine Angriffskarte ausspielt, kannst du diese Karte aus deiner Hand vorzeigen. Der Angriff hat keine Wirkung auf dich.",
				"image": "21.png"
			}
		},
		"ActionCard": {
			"31": {
				"name": "Keller",
				"description": "+ 1 Aktion, Lege eine beliebige Anzahl Karten aus deiner Hand ab. F체r jede abgelegte Karte ziehst du dann eine neue Karte nach.",
				"image": "31.png"
			},
			"32": {
				"name": "Dorf",
				"description": "+ 1 Karte, + 2 Aktionen",
				"image": "32.png"
			},
			"33": {
				"name": "Werkstatt",
				"description": "",
				"image": "33.png"
			},
			"34": {
				"name": "Holzf채ller",
				"description": "",
				"image": "34.png"
			},
			"35": {
				"name": "Schmiede",
				"description": "",
				"image": "35.png"
			},
			"36": {
				"name": "Umbau",
				"description": "",
				"image": "36.png"
			},
			"37": {
				"name": "Miliz",
				"description": "",
				"image": "37.png"
			},
			"38": {
				"name": "Markt",
				"description": "",
				"image": "38.png"
			},
			"39": {
				"name": "Mine",
				"description": "",
				"image": "39.png"
			}
		}
	}
}